{
  "filters": [
    {
   "class": "material",
   "filters": [
        { "label": "Amate", "value": "amate" },
        { "label": "Tulle", "value": "tulle" },
        { "label": "Tulle Natural", "value": "tulle-natural" },
        { "label": "Tulle Deslavado", "value": "tulle-deslavado" },
        { "label": "Tulle Decorado", "value": "tulle-natural-decorado" },
        { "label": "Amate Liso", "value": "amate-liso" }
      ]
    }, {
   "class": "accesories",
   "filters": [
        { "label": "Enmarcados", "value": "marco" },
        { "label": "Herreria", "value": "herreria", "filter-class": "accesories" },
        { "label": "Marco Ola", "value": "marco-ola", "filter-class": "accesories" },
        { "label": "Marco Cajon L", "value": "marco-cajon-L", "filter-class": "accesories" },
        { "label": "Marco Cajon", "value": "marco-cajon", "filter-class": "accesories" },
        { "label": "Marco L Invertido", "value": "marco-L-invertido", "filter-class": "accesories" }
      ]
    }, {
   "class": "other",
   "filters": [
        { "label": "Tejidos", "value": "tejidos" },
        { "label": "Blanco Natural", "value": "blanco-natural" }
      ]
    }
  ],
  "images": [
    {"folder": "images/gallery/02", "name": "04-a.jpg", "categories": " marco marco-ola amate, tejidos blanco-natural "},
    {"folder": "images/gallery/02", "name": "04-b.jpg", "categories": " marco marco-ola amate, tejidos blanco-natural "},
    {"folder": "images/gallery/02", "name": "05-a.jpg", "categories": " marco marco-ola amate, tejidos blanco-natural "},
    {"folder": "images/gallery/02", "name": "05-b.jpg", "categories": " marco marco-ola amate, tejidos blanco-natural "},
    {"folder": "images/gallery/02", "name": "08-a.jpg", "categories": " marco amate, tejidos marco-cajon-L "},
    {"folder": "images/gallery/02", "name": "09-a.jpg", "categories": " marco amate, tejidos marco-cajon-L "},
    {"folder": "images/gallery/02", "name": "09-b.jpg", "categories": " marco amate, tejidos marco-cajon-L "},
    {"folder": "images/gallery/02", "name": "10-a.jpg", "categories": " marco amate, tejidos marco-cajon-L "},
    {"folder": "images/gallery/02", "name": "10-b.jpg", "categories": " marco amate, tejidos marco-cajon-L "},
    {"folder": "images/gallery/02", "name": "106-a.jpg ", "categories": " marco amate, tejidos marco-de-galeria "},
    {"folder": "images/gallery/02", "name": "106-b.jpg ", "categories": " marco amate, tejidos marco-de-galeria "},
    {"folder": "images/gallery/02", "name": "107-a.jpg ", "categories": " marco amate, tejidos marco-de-galeria "},
    {"folder": "images/gallery/02", "name": "107-b.jpg ", "categories": " marco amate, tejidos marco-de-galeria "},
    {"folder": "images/gallery/02", "name": "108-a.jpg ", "categories": " marco amate, tejidos marco-de-galeria "},
    {"folder": "images/gallery/02", "name": "108-b.jpg ", "categories": " marco amate, tejidos marco-de-galeria "},
    {"folder": "images/gallery/02", "name": "11-a.jpg", "categories": " marco tejidos marco-cajon-L "},
    {"folder": "images/gallery/02", "name": "11-b.jpg", "categories": " marco tejidos marco-cajon-L "},

    {"folder": "images/gallery/01", "name": "TD3-101-a.jpg", "categories": " marco herreria tulle tulle-deslavado"},
    {"folder": "images/gallery/01", "name": "TD3-101-b.jpg", "categories": " marco herreria tulle tulle-deslavado"},
    {"folder": "images/gallery/01", "name": "TD3-102-a.jpg", "categories": " marco herreria tulle tulle-deslavado"},
    {"folder": "images/gallery/01", "name": "TD3-102-b.jpg", "categories": " marco herreria tulle tulle-deslavado"},
    {"folder": "images/gallery/01", "name": "TD3-103-a.jpg", "categories": " marco herreria tulle tulle-deslavado"},
    {"folder": "images/gallery/01", "name": "TD3-103-b.jpg", "categories": " marco herreria tulle tulle-deslavado"},
    {"folder": "images/gallery/01", "name": "TD3-104-a.jpg", "categories": " marco herreria tulle tulle-deslavado"},
    {"folder": "images/gallery/01", "name": "TD3-104-b.jpg", "categories": " marco herreria tulle tulle-deslavado"},
    {"folder": "images/gallery/01", "name": "TD3-105-a.jpg", "categories": " marco herreria tulle tulle-deslavado"},
    {"folder": "images/gallery/01", "name": "TD3-105-b.jpg", "categories": " marco herreria tulle tulle-deslavado"},
    {"folder": "images/gallery/01", "name": "TD3-106-a.jpg", "categories": " marco herreria tulle tulle-deslavado"},
    {"folder": "images/gallery/01", "name": "TD3-106-b.jpg", "categories": " marco herreria tulle tulle-deslavado"},
    {"folder": "images/gallery/01", "name": "TD3-107-a.jpg", "categories": " marco herreria tulle tulle-deslavado"},
    {"folder": "images/gallery/01", "name": "TD3-107-b.jpg", "categories": " marco herreria tulle tulle-deslavado"},
    {"folder": "images/gallery/01", "name": "TD3-108-a.jpg", "categories": " marco herreria tulle tulle-deslavado"},
    {"folder": "images/gallery/01", "name": "TD3-108-b.jpg", "categories": " marco herreria tulle tulle-deslavado"},
    {"folder": "images/gallery/01", "name": "TD3-109-a.jpg", "categories": " marco herreria tulle tulle-deslavado"},
    {"folder": "images/gallery/01", "name": "TD3-109-b.jpg", "categories": " marco herreria tulle tulle-deslavado"},
    {"folder": "images/gallery/01", "name": "TD3-110-a.jpg", "categories": " marco herreria tulle tulle-deslavado"},
    {"folder": "images/gallery/01", "name": "TD3-110-b.jpg", "categories": " marco herreria tulle tulle-deslavado"},
    {"folder": "images/gallery/01", "name": "TN3-101-a.jpg", "categories": " marco herreria tulle tulle-natural "},
    {"folder": "images/gallery/01", "name": "TN3-102-a.jpg", "categories": " marco herreria tulle tulle-natural "},
    {"folder": "images/gallery/01", "name": "TN3-103-a.jpg", "categories": " marco herreria tulle tulle-natural "},
    {"folder": "images/gallery/01", "name": "TN3-104-a.jpg", "categories": " marco herreria tulle tulle-natural "},
    {"folder": "images/gallery/01", "name": "TN3-105-a.jpg", "categories": " marco herreria tulle tulle-natural "},
    {"folder": "images/gallery/01", "name": "TN3-107-a.jpg", "categories": " marco herreria tulle tulle-natural "},
    {"folder": "images/gallery/01", "name": "TN3-108-a.jpg", "categories": " marco herreria tulle tulle-natural "},
    {"folder": "images/gallery/01", "name": "TN3-109-a.jpg", "categories": " marco herreria tulle tulle-natural "},
    {"folder": "images/gallery/01", "name": "TN3-110-a.jpg", "categories": " marco herreria tulle tulle-natural "},
    {"folder": "images/gallery/01", "name": "TN3-118-a.jpg", "categories": " marco herreria tulle tulle-natural "},
    {"folder": "images/gallery/01", "name": "TN3-118-b.jpg", "categories": " marco herreria tulle tulle-natural "},
    {"folder": "images/gallery/01", "name": "TN3-119-a.jpg", "categories": " marco herreria tulle tulle-natural "},
    {"folder": "images/gallery/01", "name": "TN3-119-b.jpg", "categories": " marco herreria tulle tulle-natural "},
    {"folder": "images/gallery/01", "name": "TND3-120-a.jpg", "categories": " marco herreria tulle tulle-natural-decorado"},
    {"folder": "images/gallery/01", "name": "TND3-120-b.jpg", "categories": " marco herreria tulle tulle-natural-decorado"},
    {"folder": "images/gallery/01", "name": "TND3-121-a.jpg", "categories": " marco herreria tulle tulle-natural-decorado"},
    {"folder": "images/gallery/01", "name": "TND3-121-b.jpg", "categories": " marco herreria tulle tulle-natural-decorado"},
    {"folder": "images/gallery/01", "name": "TND3-122-a.jpg", "categories": " marco herreria tulle tulle-natural-decorado"},
    {"folder": "images/gallery/01", "name": "TND3-122-b.jpg", "categories": " marco herreria tulle tulle-natural-decorado"},
    {"folder": "images/gallery/01", "name": "TND3-123-a.jpg", "categories": " marco herreria tulle tulle-natural-decorado"},
    {"folder": "images/gallery/01", "name": "TND3-123-b.jpg", "categories": " marco herreria tulle tulle-natural-decorado"},
    {"folder": "images/gallery/01", "name": "TND3-124-a.jpg", "categories": " marco herreria tulle tulle-natural-decorado"},
    {"folder": "images/gallery/01", "name": "TND3-124-b.jpg", "categories": " marco herreria tulle tulle-natural-decorado"},
    {"folder": "images/gallery/01", "name": "TND3-125-a.jpg", "categories": " marco herreria tulle tulle-natural-decorado"},
    {"folder": "images/gallery/01", "name": "TND3-125-b.jpg", "categories": " marco herreria tulle tulle-natural-decorado"},
    {"folder": "images/gallery/01", "name": "TND3-126-a.jpg", "categories": " marco herreria tulle tulle-natural-decorado"},
    {"folder": "images/gallery/01", "name": "TND3-126-b.jpg", "categories": " marco herreria tulle tulle-natural-decorado"},
    {"folder": "images/gallery/01", "name": "TND3-127-a.jpg", "categories": " marco herreria tulle tulle-natural-decorado"},
    {"folder": "images/gallery/01", "name": "TND3-127-b.jpg", "categories": " marco herreria tulle tulle-natural-decorado"},
    {"folder": "images/gallery/01", "name": "TND3-128-a.jpg", "categories": " marco herreria tulle tulle-natural-decorado"},
    {"folder": "images/gallery/01", "name": "TND3-129-a.jpg", "categories": " marco herreria tulle tulle-natural-decorado"},
    {"folder": "images/gallery/01", "name": "TND3-130-a.jpg", "categories": " marco herreria tulle tulle-natural-decorado"},
    {"folder": "images/gallery/01", "name": "TND3-130-b.jpg", "categories": " marco herreria tulle tulle-natural-decorado"},

    {"folder": "images/gallery/03", "name": "01.jpg", "categories": "marco amate tejidos marco-cajon"},
    {"folder": "images/gallery/03", "name": "06.jpg", "categories": "marco amate marco-cajon"},
    {"folder": "images/gallery/03", "name": "11-a.jpg", "categories": "marco amate marco-cajon"},
    {"folder": "images/gallery/03", "name": "11-b.jpg", "categories": "marco amate marco-cajon"},
    {"folder": "images/gallery/03", "name": "12-a.jpg", "categories": "marco amate marco-cajon"},
    {"folder": "images/gallery/03", "name": "12-b.jpg", "categories": "marco amate marco-cajon"},
    {"folder": "images/gallery/03", "name": "14-a.jpg", "categories": "marco amate marco-cajon"},
    {"folder": "images/gallery/03", "name": "14-b.jpg", "categories": "marco amate marco-cajon"},
    {"folder": "images/gallery/03", "name": "15-a.jpg", "categories": "marco amate marco-cajon"},
    {"folder": "images/gallery/03", "name": "15-b.jpg", "categories": "marco amate marco-cajon"},
    {"folder": "images/gallery/03", "name": "17-a.jpg", "categories": "marco amate marco-cajon"},
    {"folder": "images/gallery/03", "name": "17-b.jpg", "categories": "marco amate marco-cajon"},
    {"folder": "images/gallery/03", "name": "24-a.jpg", "categories": "marco amate marco-L-invertido"},
    {"folder": "images/gallery/03", "name": "24-b.jpg", "categories": "marco amate marco-L-invertido"},
    {"folder": "images/gallery/03", "name": "27-a.jpg", "categories": "marco amate marco-L-invertido"},
    {"folder": "images/gallery/03", "name": "27-b.jpg", "categories": "marco amate marco-L-invertido"},
    {"folder": "images/gallery/03", "name": "28-a.jpg", "categories": "marco amate marco-L-invertido"},
    {"folder": "images/gallery/03", "name": "28-b.jpg", "categories": "marco amate marco-L-invertido"},
    {"folder": "images/gallery/03", "name": "29-a.jpg", "categories": "marco amate marco-L-invertido"},
    {"folder": "images/gallery/03", "name": "29-b.jpg", "categories": "marco amate marco-L-invertido"},
    {"folder": "images/gallery/03", "name": "30-a.jpg", "categories": "marco tule tulle-deslavado marco-cajon"},
    {"folder": "images/gallery/03", "name": "30-b.jpg", "categories": "marco tule tulle-deslavado marco-cajon"}

  ]
}